ab_py/__init__.py
ab_py/common/__init__.py
ab_py/common/ab_exception.py
ab_py/common/sdk_conf.py
ab_py/common/sdk_console.py
ab_py/common/sdk_const.py
ab_py/common/sdk_util.py
ab_py/exsited/__init__.py
ab_py/exsited/exsited_sdk.py
ab_py/exsited/account/__init__.py
ab_py/exsited/account/account.py
ab_py/exsited/account/account_api_url.py
ab_py/exsited/account/dto/__init__.py
ab_py/exsited/account/dto/account_dto.py
ab_py/exsited/account/dto/account_nested_dto.py
ab_py/exsited/auth/__init__.py
ab_py/exsited/auth/auth_api_url.py
ab_py/exsited/auth/dto/__init__.py
ab_py/exsited/auth/dto/token_dto.py
ab_py/exsited/common/__init__.py
ab_py/exsited/common/common_api_url.py
ab_py/exsited/common/common_enum.py
ab_py/exsited/common/dto/__init__.py
ab_py/exsited/common/dto/common_dto.py
ab_py/exsited/invoice/__init__.py
ab_py/exsited/invoice/invoice.py
ab_py/exsited/invoice/invoice_api_url.py
ab_py/exsited/invoice/dto/__init__.py
ab_py/exsited/invoice/dto/invoice_dto.py
ab_py/exsited/order/__init__.py
ab_py/exsited/order/order.py
ab_py/exsited/order/order_api_url.py
ab_py/exsited/order/dto/__init__.py
ab_py/exsited/order/dto/order_dto.py
ab_py/exsited/order/dto/order_nested_dto.py
ab_py/exsited/order/dto/usage_dto.py
ab_py/exsited/payment/__init__.py
ab_py/exsited/payment/payment.py
ab_py/exsited/payment/payment_api_url.py
ab_py/exsited/payment/dto/__init__.py
ab_py/exsited/payment/dto/payment_dto.py
ab_py/exsited/purchase_order/__init__.py
ab_py/exsited/purchase_order/purchase_order.py
ab_py/exsited/purchase_order/purchase_order_api_url.py
ab_py/exsited/purchase_order/dto/__init__.py
ab_py/exsited/purchase_order/dto/purchase_order_dto.py
ab_py/exsited/setting/__init__.py
ab_py/exsited/setting/setting.py
ab_py/exsited/setting/setting_api_url.py
ab_py/http/__init__.py
ab_py/http/ab_rest_processor.py
ab_py/http/http_const.py
ab_py/http/http_requester.py
ab_py/sdlize/__init__.py
ab_py/sdlize/ab_base_dto.py
ab_py/sdlize/dto_base.py
ab_py-2.0.0.dist-info/LICENSE.txt
ab_py-2.0.0.dist-info/METADATA
ab_py-2.0.0.dist-info/WHEEL
ab_py-2.0.0.dist-info/top_level.txt
ab_py-2.0.0.dist-info/RECORD
