Metadata-Version: 2.1
Name: ab_py
Version: 2.0.0
Summary: This is the sdk support for account
Home-page: https://github.com/exsited/exsited-python
Author: Kawsar Ahmad
Author-email: nmkwsr@gmail.com
Platform: any
Classifier: Programming Language :: Python :: 3
Classifier: License :: OSI Approved :: MIT License
Classifier: Operating System :: OS Independent
License-File: LICENSE.txt
Requires-Dist: requests==2.31.0
Requires-Dist: setuptools
Requires-Dist: peewee
Requires-Dist: mysql-connector-python
